argmerge/__init__.py
argmerge/base.py
argmerge/cli.py
argmerge/decorator.py
argmerge/env.py
argmerge/func.py
argmerge/json.py
argmerge/py.typed
argmerge/trace.py
argmerge/utils.py
argmerge/yaml.py
argmerge-0.0.4.dist-info/METADATA
argmerge-0.0.4.dist-info/WHEEL
argmerge-0.0.4.dist-info/licenses/LICENSE
argmerge-0.0.4.dist-info/RECORD
