Metadata-Version: 2.4
Name: argmerge
Version: 0.0.4
Summary: Merge arguments from outside your program before they reach your program.
Author-email: duck-bongos <billmannd@gmail.com>
License-File: LICENSE
Classifier: Development Status :: 3 - Alpha
Classifier: Intended Audience :: Developers
Classifier: Programming Language :: Python
Classifier: Programming Language :: Python :: 3
Classifier: Programming Language :: Python :: 3 :: Only
Classifier: Programming Language :: Python :: 3.10
Classifier: Programming Language :: Python :: 3.11
Classifier: Programming Language :: Python :: 3.12
Classifier: Programming Language :: Python :: 3.13
Requires-Python: >=3.10
Requires-Dist: loguru>=0.7.3
Requires-Dist: mkdocs-material>=9.6.21
Requires-Dist: pydantic>=2.12.2
Requires-Dist: pyyaml>=6.0.3
Provides-Extra: documentation
Requires-Dist: mkdocs-autoapi>=0.4.1; extra == 'documentation'
Requires-Dist: mkdocs-landing>=0.0.8; extra == 'documentation'
Requires-Dist: mkdocs-terminal>=4.7.0; extra == 'documentation'
Requires-Dist: mkdocs>=1.6.1; extra == 'documentation'
Requires-Dist: mkdocstrings[python]>=0.30.1; extra == 'documentation'
